{
    "id": "0263",
    "question": "A 35-year-old woman presents with severe fear reactions to seeing dogs after moving into a new suburban neighborhood. She states that she has always had an irrational and excessive fear of dogs but has been able to avoid it for most of her life while living in the city. When she sees her neighbors walking their dogs outside, she is terrified and begins to feel short of breath. Recently, she has stopped picking up her children from the bus stop and no longer plays outside with her children in order to avoid seeing any dogs. Which of the following would be the best definitive treatment for this patient?",
    "options": {
        "A": "Selective serotonin reuptake inhibitors (SSRIs)",
        "B": "Short-acting benzodiazepines",
        "C": "Systematic desensitization",
        "D": "Cognitive behavioral therapy"
    },
    "answer": "C",
    "predict": "{\"step_by_step_thinking\": \"To address this patient's condition, we need to consider the nature of her fear and the most effective treatment options. The patient's fear of dogs is a specific phobia, which is a type of anxiety disorder. The fact that she has been able to avoid the situation in the past but is now avoiding her daily life due to the fear is indicative of a severe phobia. The patient's avoidance behaviors are a key component of her condition, as they are reinforcing her fear and preventing her from confronting and overcoming it. The fact that she has been able to avoid dogs in the city but not in her new suburban neighborhood suggests that her fear is not just about the dogs themselves, but also about the environment and situation in which she encounters them. Selective serotonin reuptake inhibitors (SSRIs) are commonly used to treat anxiety disorders, including specific phobias. However, while they can be effective in reducing symptoms, they do not address the underlying fear and avoidance behaviors. Short-acting benzodiazepines are typically used for acute anxiety relief and are not a long-term solution for treating specific phobias. Cognitive behavioral therapy (CBT) is a type of psychotherapy that is highly effective in treating specific phobias. It involves exposure therapy, which involves gradually exposing the patient to the feared situation or object in a controlled and safe environment, while teaching coping skills and relaxation techniques to manage anxiety. This approach addresses the underlying fear and avoidance behaviors, allowing the patient to confront and overcome her phobia. Given the patient's severe avoidance behaviors and the need for a comprehensive treatment plan, CBT is the most effective treatment option for this patient.\"} \"answer_choice\": \"D\"",
    "snippets": [],
    "scores": [],
    "execution_time": 45.15742373466492
}