{
    "id": "0584",
    "question": "A 33-year-old man presents to the emergency department after a motor vehicle collision. He was the front seat unrestrained driver in a head-on collision. The patient has a Glasgow Coma Scale of 5 and is subsequently intubated. Physical exam is notable for subcutaneous emphysema in the clavicular area. Needle decompression and chest tube placement are performed, and the patient is stabilized after receiving 2 units of blood and 2 liters of fluid. Chest radiography demonstrates proper tube location and resolution of the pneumothorax. The patient is transferred to the trauma intensive care unit. On the unit, a repeat chest radiograph is notable for a recurrent pneumothorax with the chest tube in place. Which of the following is the most likely diagnosis?",
    "options": {
        "A": "Inappropriate chest tube placement",
        "B": "Spontaneous pneumothorax",
        "C": "Tension pneumothorax",
        "D": "Tracheobronchial rupture"
    },
    "answer": "D",
    "predict": "{\"step_by_step_thinking\": \"To approach this question, let's break down the key points in the patient's presentation and the information provided: 1. The patient is a 33-year-old man who was involved in a head-on motor vehicle collision as an unrestrained driver. This type of collision is known to cause significant blunt trauma, including potential injuries to the chest and lungs. 2. The patient has a Glasgow Coma Scale of 5, indicating severe brain injury, but this is not directly relevant to the respiratory or cardiovascular findings. 3. The patient is intubated and has subcutaneous emphysema in the clavicular area, which is a sign of air leak. This, combined with the need for needle decompression and chest tube placement, suggests a pneumothorax. 4. The patient receives 2 units of blood and 2 liters of fluid, indicating significant blood loss and volume depletion. However, this information does not directly relate to the current respiratory issue. 5. The initial chest radiograph shows proper tube placement and resolution of the pneumothorax, indicating that the initial intervention was successful. 6. The key piece of information that points to the correct diagnosis is the recurrent pneumothorax with the chest tube in place. This suggests that the chest tube is not adequately sealing the pneumothorax, allowing air to continue entering the pleural space. Considering these points, let's evaluate the options: - A. Inappropriate chest tube placement: This is unlikely because the initial chest radiograph showed proper tube placement. - B. Spontaneous pneumothorax: This is unlikely because the patient has a history of trauma and is intubated, which makes spontaneous pneumothorax less likely. - C. Tension pneumothorax: This is the most likely diagnosis. The recurrent pneumothorax with the chest tube in place suggests that the chest tube is not sealing the pneumothorax, which is a hallmark of tension pneumothorax. Tension pneumothorax is a life-threatening condition that requires immediate intervention. - D. Tracheobronchial rupture: This is unlikely because there is no direct evidence of air leak into the trachea or bronchi. The most likely diagnosis is C. Tension pneumothorax.\", \"answer_choice\": \"C\"}",
    "snippets": [],
    "scores": [],
    "execution_time": 73.20708107948303
}