{
    "id": "0686",
    "question": "A 3-day-old boy is brought to the emergency department because of a 4-hour history of somnolence, poor feeding, and one episode of vomiting. He is exclusively breastfed. His serum glucose concentration is 88 mg/dL and his serum ammonia concentration is 850 \u03bcmol/L (N<90). Urinalysis shows an increased orotic acid to creatinine ratio. Urinary ketones are absent. This patient is most likely deficient in an enzyme that catalyzes which of the following reactions?",
    "options": {
        "A": "Ornithine and carbamoyl phosphate to citrulline",
        "B": "Orotic acid to uridine monophosphate",
        "C": "Pyruvate to acetyl-coenzyme A",
        "D": "Glutamate and acetyl-coenzyme A to N-acetylglutamate"
    },
    "answer": "A",
    "predict": "To approach this question, let's analyze the given information step by step: 1. **Clinical Presentation**: The patient is a 3-day-old boy presenting with somnolence, poor feeding, and vomiting. These symptoms can be indicative of a metabolic disorder, especially in a neonate. 2. **Laboratory Findings**: - **Serum Glucose Concentration**: 88 mg/dL, which is lower than the normal range for a newborn. This suggests a potential issue with glucose metabolism. - **Serum Ammonia Concentration**: 850 \u03bcmol/L, which is significantly elevated (normal <90 \u03bcmol/L). Elevated ammonia levels can indicate a problem with the urea cycle or other nitrogen metabolism pathways. - **Urinalysis**: Increased orotic acid to creatinine ratio, with absent urinary ketones. The presence of orotic acid in the urine suggests a defect in pyrimidine synthesis. 3. **Metabolic Pathways**: - **Option A: Ornithine and carbamoyl phosphate to citrulline**: This is the reaction catalyzed by the enzyme ornithine transcarbamylase (OTC). OTC deficiency leads to a classic urea cycle disorder, characterized by elevated ammonia levels, which matches the patient's presentation. - **Option B: Orotic acid to uridine monophosphate**: This step involves the enzyme orotate phosphoribosyltransferase. Deficiency in this enzyme leads to orotic aciduria, but it is less likely to cause the severe metabolic disturbances seen in this patient. - **Option C: Pyruvate to acetyl-coenzyme A**: This step is part of glycolysis and gluconeogenesis, and a deficiency here would not explain the elevated ammonia levels or the specific urinary findings. - **Option D: Glutamate and acetyl-coenzyme A to N-acetylglutamate**: This reaction is part of the urea cycle and involves the enzyme glutamate dehydrogenase. However, this enzyme is not directly related to the elevated ammonia levels or orotic aciduria. Given the elevated ammonia levels, poor feeding, and the specific urinary findings, the patient is most likely deficient in an enzyme involved in the urea cycle. Among the options provided, **ornithine and carbamoyl phosphate to citrulline** is the reaction catalyzed by ornithine transcarbamylase (OTC), which is directly related to the symptoms and lab findings described. **Answer Choice**: A",
    "snippets": [],
    "scores": [],
    "execution_time": 25.164309978485107
}