{
    "id": "0711",
    "question": "An 8-year-old boy is brought to the physician because he has excessively dry skin. His mother says that he has had dry, scaly skin since he was 6 months old. She says it is worse in winter and better in summer. There is no associated itching, redness, or discharge. Examination reveals generalized fine scales with coarse skin all over the body, except in the skin creases of the neck and in the cubital and popliteal fossae (see image). There are multiple papular elevations at the base of hair follicles and darkening of the palmar and plantar creases. Which of the following is the most likely diagnosis?",
    "options": {
        "A": "Psoriasis",
        "B": "Lichen simplex",
        "C": "Ichthyosis vulgaris",
        "D": "Pityriasis versicolor"
    },
    "answer": "C",
    "predict": "{\"step_by_step_thinking\": \"To approach this case, we need to consider the key features of the patient's presentation and how they relate to the potential diagnoses. 1. The patient has had dry, scaly skin since infancy, which suggests a congenital condition. 2. The condition worsens in winter and improves in summer, which is consistent with a condition that is exacerbated by cold, dry air. 3. The absence of itching, redness, or discharge makes conditions like eczema or dermatitis less likely. 4. The distribution of the scales is generalized, with the exception of the skin creases of the neck and cubital and popliteal fossae, which is a characteristic feature of ichthyosis. 5. The presence of papular elevations at the base of hair follicles and darkening of the palmar and plantar creases are also consistent with ichthyosis. Given these features, we can evaluate the potential diagnoses: * Psoriasis (A) is unlikely because it typically presents with well-defined, scaly plaques that are often itchy and can be localized to specific areas of the body. It is also not typically congenital. * Lichen simplex (B) is unlikely because it is a condition characterized by intense itching and is not typically present at birth. * Pityriasis versicolor (D) is unlikely because it is a fungal infection that typically presents with macular patches that are lighter or darker than the surrounding skin, and is not typically present at birth. * Ichthyosis vulgaris (C) is the most likely diagnosis because it is a congenital condition characterized by dry, scaly skin that worsens in cold, dry air and improves in warm, humid environments. It is also consistent with the distribution and characteristics of the patient's skin lesions. Therefore, the most likely diagnosis is ichthyosis vulgaris.\"} \"answer_choice\": \"C\"",
    "snippets": [],
    "scores": [],
    "execution_time": 19.741204023361206
}