{
    "id": "622632483a8413c653000081",
    "question": "Is disruption of immune regulation mechanisms associated with adverse pregnancy outcomes, including preeclampsia (PE)?",
    "options": {
        "A": "yes",
        "B": "no"
    },
    "answer": "A",
    "predict": "{\"step_by_step_thinking\": \"To answer this question, we need to consider the role of immune regulation mechanisms during pregnancy and their potential impact on pregnancy outcomes, particularly preeclampsia (PE). Preeclampsia is a pregnancy complication characterized by high blood pressure and damage to organs such as the kidneys and liver. Immune regulation mechanisms play a crucial role in maintaining a healthy pregnancy by preventing the mother's immune system from attacking the fetus. Disruption of these mechanisms can lead to an imbalance in the immune response, which may contribute to the development of preeclampsia and other pregnancy complications.\\n\\nResearch has shown that alterations in immune function, such as increased inflammation and immune cell activation, are common in women with preeclampsia. These changes can disrupt the normal regulation of the immune response, leading to the release of pro-inflammatory cytokines and the activation of immune cells that can damage the placenta and other organs.\\n\\nFurthermore, studies have identified several immune-related genes and pathways that are associated with preeclampsia, including those involved in the regulation of angiogenesis, coagulation, and apoptosis. Disruption of these mechanisms can lead to the characteristic symptoms of preeclampsia, such as hypertension and proteinuria.\\n\\nIn addition, immune regulation mechanisms are not only critical for preventing preeclampsia but also for maintaining a healthy pregnancy. Dysregulation of these mechanisms can lead to other pregnancy complications, including preterm birth, low birth weight, and fetal growth restriction.\\n\\nIn conclusion, the evidence suggests that disruption of immune regulation mechanisms is indeed associated with adverse pregnancy outcomes, including preeclampsia. This understanding has important implications for the development of new therapeutic strategies to prevent and treat preeclampsia and other pregnancy complications.\", \"answer_choice\": \"A\"}",
    "snippets": [],
    "scores": [],
    "execution_time": 21.526614665985107
}