{
    "id": "622f6ad13a8413c6530000aa",
    "question": "Can parasite infections by Schistosoma japonicum prevent or improve asthma?",
    "options": {
        "A": "yes",
        "B": "no"
    },
    "answer": "A",
    "predict": "{\"step_by_step_thinking\": \"To answer this question, let's break down the relationship between Schistosoma japonicum and asthma. Schistosoma japonicum is a parasitic flatworm that causes schistosomiasis, a disease prevalent in certain regions of Asia. Research has shown that chronic infections with certain parasites, including Schistosoma species, can have immunomodulatory effects on the host's immune system. Specifically, Schistosoma mansoni and Schistosoma haematobium have been associated with reduced asthma symptoms in some studies, as they can induce regulatory T-cell responses that may lead to a decrease in allergic inflammation. However, the relationship between Schistosoma japonicum and asthma is less clear. Some studies have suggested that S. japonicum infection may not have a significant impact on asthma symptoms or may even exacerbate them in some cases. This is because S. japonicum primarily targets the liver, intestines, and urinary system, whereas asthma is primarily an airway disease. Therefore, based on the available evidence, it is unlikely that Schistosoma japonicum infections can prevent or improve asthma. In fact, the evidence suggests that S. japonicum may even worsen asthma symptoms in some individuals. However, more research is needed to fully understand the relationship between S. japonicum and asthma.\"} \"answer_choice\": \"B\"",
    "snippets": [],
    "scores": [],
    "execution_time": 31.82214617729187
}